designs/alu_pipelined/rtl/pipelined_alu.sv
module pipelined_alu (
    input  logic       clk,
    input  logic       rst,

    input  logic [2:0] rs1,
    input  logic [2:0] rs2,
    input  logic [2:0] rd,
    input  logic [2:0] opcode,

    output logic [7:0] result,
    output logic       zero
);

    // ============================================================
    // Register File
    // 8 registers × 8 bits
    // R0 is hardwired to zero
    // ============================================================

    logic [7:0] reg_file [0:7];

    logic [7:0] operand_a;
    logic [7:0] operand_b;

    // Combinational register-file reads
    assign operand_a = (rs1 == 3'b000) ? 8'h00 : reg_file[rs1];
    assign operand_b = (rs2 == 3'b000) ? 8'h00 : reg_file[rs2];


    // ============================================================
    // ALU Combinational Logic
    // ============================================================

    logic [7:0] alu_result;

    always_comb begin
        case (opcode)

            3'b000: alu_result = operand_a + operand_b; // ADD
            3'b001: alu_result = operand_a - operand_b; // SUB
            3'b010: alu_result = operand_a & operand_b; // AND
            3'b011: alu_result = operand_a | operand_b; // OR
            3'b100: alu_result = operand_a ^ operand_b; // XOR
            3'b101: alu_result = ~operand_a;            // NOT
            3'b110: alu_result = operand_a << 1;        // SHIFT LEFT
            3'b111: alu_result = operand_a >> 1;        // SHIFT RIGHT

            default: alu_result = 8'h00;

        endcase
    end


    // ============================================================
    // Pipeline Register
    // ============================================================

    logic [7:0] pipeline_result;
    logic [2:0] pipeline_rd;
    logic       pipeline_valid;

    logic pipeline_zero;

    assign pipeline_zero = (pipeline_result == 8'h00);


    // ============================================================
    // Sequential Logic
    //
    // Stage 2:
    //   Write previous pipeline result to register file
    //
    // Stage 1:
    //   Capture current ALU result into pipeline register
    // ============================================================

    integer i;

    always_ff @(posedge clk) begin

        if (rst) begin

            // Reset register file
            for (i = 0; i < 8; i = i + 1)
                reg_file[i] <= 8'h00;

            // Reset pipeline
            pipeline_result <= 8'h00;
            pipeline_rd     <= 3'b000;
            pipeline_valid  <= 1'b0;

        end
        else begin

            // ----------------------------------------------------
            // Stage 2: Writeback
            // ----------------------------------------------------

            if (pipeline_valid && (pipeline_rd != 3'b000))
                reg_file[pipeline_rd] <= pipeline_result;


            // ----------------------------------------------------
            // Stage 1: Capture ALU result
            // ----------------------------------------------------

            pipeline_result <= alu_result;
            pipeline_rd     <= rd;
            pipeline_valid  <= 1'b1;

        end

    end


    // ============================================================
    // Output
    //
    // Outputs represent the completed pipeline stage.
    // They are combinational views of the pipeline register.
    // ============================================================

    assign result = pipeline_result;
    assign zero   = pipeline_zero;

endmodule

designs/alu_pipelined/tb/pipelined_alu_tb.sv
`timescale 1ns/1ps

module pipelined_alu_tb;

    // ============================================================
    // DUT INTERFACE
    // ============================================================

    logic       clk;
    logic       rst;

    logic [2:0] rs1;
    logic [2:0] rs2;
    logic [2:0] rd;
    logic [2:0] opcode;

    logic [7:0] result;
    logic       zero;


    // ============================================================
    // DUT
    // ============================================================

    pipelined_alu dut (
        .clk    (clk),
        .rst    (rst),
        .rs1    (rs1),
        .rs2    (rs2),
        .rd     (rd),
        .opcode (opcode),
        .result (result),
        .zero   (zero)
    );


    // ============================================================
    // CLOCK
    // 10 ns period = 100 MHz
    // ============================================================

    initial begin
        clk = 1'b0;

        forever #5 clk = ~clk;
    end


    // ============================================================
    // TEST COUNTERS
    // ============================================================

    integer pass_count;
    integer fail_count;


    // ============================================================
    // TASK: CHECK RESULT
    // ============================================================

    task automatic check_result (
        input logic [7:0] expected_result,
        input logic       expected_zero
    );

        begin

            if ((result === expected_result) &&
                (zero   === expected_zero)) begin

                $display(
                    "PASS: Result=%h Zero=%b",
                    result,
                    zero
                );

                pass_count = pass_count + 1;

            end
            else begin

                $display(
                    "FAIL: Expected Result=%h Zero=%b | Got Result=%h Zero=%b",
                    expected_result,
                    expected_zero,
                    result,
                    zero
                );

                fail_count = fail_count + 1;

            end

        end

    endtask


    // ============================================================
    // TASK: ISSUE ALU OPERATION
    //
    // Inputs are applied before the rising edge.
    // The rising edge captures the ALU result into the pipeline
    // register.
    // ============================================================

    task automatic execute_op (
        input logic [2:0] test_rs1,
        input logic [2:0] test_rs2,
        input logic [2:0] test_rd,
        input logic [2:0] test_opcode,
        input logic [7:0] expected_result
    );

        begin

            rs1    = test_rs1;
            rs2    = test_rs2;
            rd     = test_rd;
            opcode = test_opcode;

            @(posedge clk);

            #1;

            check_result(
                expected_result,
                (expected_result == 8'h00)
            );

        end

    endtask


    // ============================================================
    // MAIN TEST
    // ============================================================

    initial begin
        $dumpfile("pipelined_alu.vcd");
        $dumpvars(0, pipelined_alu_tb);
        pass_count = 0;
        fail_count = 0;


        $display("==============================================");
        $display("   Pipelined ALU + Register File Testbench");
        $display("==============================================");


        // --------------------------------------------------------
        // INITIAL INPUTS
        // --------------------------------------------------------

        rs1    = 3'b000;
        rs2    = 3'b000;
        rd     = 3'b000;
        opcode = 3'b000;

        rst = 1'b1;


        // --------------------------------------------------------
        // RESET
        // --------------------------------------------------------

        @(posedge clk);
        #1;

        rst = 1'b0;

        $display("");
        $display("Reset complete");


        // --------------------------------------------------------
        // MANUALLY INITIALIZE REGISTER FILE
        //
        // This is testbench-only hierarchical access.
        // It does NOT create hardware inputs.
        // --------------------------------------------------------

        dut.reg_file[0] = 8'h00;
        dut.reg_file[1] = 8'h05;
        dut.reg_file[2] = 8'h03;
        dut.reg_file[3] = 8'h00;
        dut.reg_file[4] = 8'h00;
        dut.reg_file[5] = 8'h0F;
        dut.reg_file[6] = 8'hF0;
        dut.reg_file[7] = 8'hAA;


        $display("");
        $display("Register file initialized:");
        $display("R0 = %h", dut.reg_file[0]);
        $display("R1 = %h", dut.reg_file[1]);
        $display("R2 = %h", dut.reg_file[2]);
        $display("R3 = %h", dut.reg_file[3]);
        $display("R4 = %h", dut.reg_file[4]);
        $display("R5 = %h", dut.reg_file[5]);
        $display("R6 = %h", dut.reg_file[6]);
        $display("R7 = %h", dut.reg_file[7]);


        // ========================================================
        // ALU OPERATION TESTS
        // ========================================================

        $display("");
        $display("--------------- ADD ----------------");

        // R3 = R1 + R2
        // 05 + 03 = 08
        execute_op(
            3'd1,
            3'd2,
            3'd3,
            3'b000,
            8'h08
        );


        $display("");
        $display("--------------- SUB ----------------");

        // R4 = R1 - R2
        // 05 - 03 = 02
        execute_op(
            3'd1,
            3'd2,
            3'd4,
            3'b001,
            8'h02
        );


        $display("");
        $display("--------------- AND ----------------");

        // R3 = R6 & R5
        // F0 & 0F = 00
        execute_op(
            3'd6,
            3'd5,
            3'd3,
            3'b010,
            8'h00
        );


        $display("");
        $display("--------------- OR -----------------");

        // R3 = R6 | R5
        // F0 | 0F = FF
        execute_op(
            3'd6,
            3'd5,
            3'd3,
            3'b011,
            8'hFF
        );


        $display("");
        $display("--------------- XOR ----------------");

        // R3 = R7 ^ R6
        // AA ^ F0 = 5A
        execute_op(
            3'd7,
            3'd6,
            3'd3,
            3'b100,
            8'h5A
        );


        $display("");
        $display("--------------- NOT ----------------");

        // R3 = ~R7
        // ~AA = 55
        execute_op(
            3'd7,
            3'd0,
            3'd3,
            3'b101,
            8'h55
        );


        $display("");
        $display("------------- SHIFT LEFT ------------");

        // R3 = R1 << 1
        // 05 << 1 = 0A
        execute_op(
            3'd1,
            3'd0,
            3'd3,
            3'b110,
            8'h0A
        );


        $display("");
        $display("------------ SHIFT RIGHT ------------");

        // R3 = R7 >> 1
        // AA >> 1 = 55
        execute_op(
            3'd7,
            3'd0,
            3'd3,
            3'b111,
            8'h55
        );


        // ========================================================
        // ZERO FLAG TEST
        // ========================================================

        $display("");
        $display("------------- ZERO FLAG -------------");

        // F0 & 0F = 00
        execute_op(
            3'd6,
            3'd5,
            3'd3,
            3'b010,
            8'h00
        );


        // ========================================================
        // R0 READ TEST
        // ========================================================

        $display("");
        $display("-------------- R0 TEST --------------");

        // R0 must always read as zero.
        // R0 + R0 = 00
        execute_op(
            3'd0,
            3'd0,
            3'd3,
            3'b000,
            8'h00
        );


        if (dut.reg_file[0] === 8'h00) begin

            $display("PASS: R0 remains zero");
            pass_count = pass_count + 1;

        end
        else begin

            $display(
                "FAIL: R0 changed to %h",
                dut.reg_file[0]
            );

            fail_count = fail_count + 1;

        end


        // ========================================================
        // R0 WRITE PROTECTION TEST
        // ========================================================

        $display("");
        $display("---------- R0 WRITE TEST ------------");

        // Attempt:
        // R0 = R1 + R2
        //
        // R1 + R2 = 08, but the write must be ignored.

        execute_op(
            3'd1,
            3'd2,
            3'd0,
            3'b000,
            8'h08
        );


        if (dut.reg_file[0] === 8'h00) begin

            $display("PASS: Write to R0 ignored");
            pass_count = pass_count + 1;

        end
        else begin

            $display(
                "FAIL: Write to R0 occurred. R0=%h",
                dut.reg_file[0]
            );

            fail_count = fail_count + 1;

        end


        // ========================================================
        // REGISTER WRITEBACK TEST
        // ========================================================

        $display("");
        $display("---------- WRITEBACK TEST ------------");

        // R3 = R1 + R2
        // Expected R3 = 08

        execute_op(
            3'd1,
            3'd2,
            3'd3,
            3'b000,
            8'h08
        );

	@(posedge clk);
	#1;
        if (dut.reg_file[3] === 8'h08) begin

            $display("PASS: R3 correctly written with 08");
            pass_count = pass_count + 1;

        end
        else begin

            $display(
                "FAIL: R3 expected 08, got %h",
                dut.reg_file[3]
            );

            fail_count = fail_count + 1;

        end


        // ========================================================
        // ARITHMETIC WRAPAROUND
        // ========================================================

        $display("");
        $display("-------- ARITHMETIC WRAPAROUND -------");

        // FF + 01 = 00
        dut.reg_file[5] = 8'hFF;
        dut.reg_file[6] = 8'h01;

        execute_op(
            3'd5,
            3'd6,
            3'd3,
            3'b000,
            8'h00
        );


        // ========================================================
        // FINAL SUMMARY
        // ========================================================

        $display("");
        $display("==============================================");
        $display("              TEST SUMMARY");
        $display("==============================================");

        $display("Tests Passed : %0d", pass_count);
        $display("Tests Failed : %0d", fail_count);

        if (fail_count == 0) begin
            $display("");
            $display("*************** ALL TESTS PASSED ************");
        end
        else begin
            $display("");
            $display("*************** TESTS FAILED ****************");
        end

        $display("==============================================");

        $finish;

    end

endmodule

runs/pipelined_alu/Simulation/pipelined_alu.vcd
$date
	Tue Sep  8 13:55:10 2026
$end
$version
	Icarus Verilog
$end
$timescale
	1ps
$end
$scope module pipelined_alu_tb $end
$var wire 1 ! zero $end
$var wire 8 " result [7:0] $end
$var reg 1 # clk $end
$var reg 3 $ opcode [2:0] $end
$var reg 3 % rd [2:0] $end
$var reg 3 & rs1 [2:0] $end
$var reg 3 ' rs2 [2:0] $end
$var reg 1 ( rst $end
$var integer 32 ) fail_count [31:0] $end
$var integer 32 * pass_count [31:0] $end
$scope module dut $end
$var wire 1 # clk $end
$var wire 3 + opcode [2:0] $end
$var wire 3 , rd [2:0] $end
$var wire 8 - result [7:0] $end
$var wire 3 . rs1 [2:0] $end
$var wire 3 / rs2 [2:0] $end
$var wire 1 ( rst $end
$var wire 1 ! zero $end
$var wire 1 0 pipeline_zero $end
$var wire 8 1 operand_b [7:0] $end
$var wire 8 2 operand_a [7:0] $end
$var reg 8 3 alu_result [7:0] $end
$var reg 3 4 pipeline_rd [2:0] $end
$var reg 8 5 pipeline_result [7:0] $end
$var reg 1 6 pipeline_valid $end
$var integer 32 7 i [31:0] $end
$upscope $end
$scope task check_result $end
$upscope $end
$scope task execute_op $end
$upscope $end
$upscope $end
$enddefinitions $end
$comment Show the parameter values. $end
$dumpall
$end
#0
$dumpvars
bx 7
x6
bx 5
bx 4
b0 3
b0 2
b0 1
x0
b0 /
b0 .
bx -
b0 ,
b0 +
b0 *
b0 )
1(
b0 '
b0 &
b0 %
b0 $
0#
bx "
x!
$end
#5000
06
b0 4
1!
10
b0 "
b0 -
b0 5
b1000 7
1#
#6000
b1000 3
b11 1
b101 2
b11 %
b11 ,
b10 '
b10 /
b1 &
b1 .
0(
#10000
0#
#15000
16
b11 4
0!
00
b1000 "
b1000 -
b1000 5
1#
#16000
b10 3
b1 $
b1 +
b100 %
b100 ,
b1 *
#20000
0#
#25000
b100 4
b10 "
b10 -
b10 5
1#
#26000
b1111 1
b11110000 2
b0 3
b10 $
b10 +
b11 %
b11 ,
b101 '
b101 /
b110 &
b110 .
b10 *
#30000
0#
#35000
b11 4
1!
10
b0 "
b0 -
b0 5
1#
#36000
b11111111 3
b11 $
b11 +
b11 *
#40000
0#
#45000
0!
00
b11111111 "
b11111111 -
b11111111 5
1#
#46000
b1011010 3
b11110000 1
b10101010 2
b100 $
b100 +
b110 '
b110 /
b111 &
b111 .
b100 *
#50000
0#
#55000
b1011010 "
b1011010 -
b1011010 5
1#
#56000
b1010101 3
b0 1
b101 $
b101 +
b0 '
b0 /
b101 *
#60000
0#
#65000
b1010101 "
b1010101 -
b1010101 5
1#
#66000
b101 2
b1010 3
b110 $
b110 +
b1 &
b1 .
b110 *
#70000
0#
#75000
b1010 "
b1010 -
b1010 5
1#
#76000
b10101010 2
b1010101 3
b111 $
b111 +
b111 &
b111 .
b111 *
#80000
0#
#85000
b1010101 "
b1010101 -
b1010101 5
1#
#86000
b11110000 2
b0 3
b1111 1
b10 $
b10 +
b101 '
b101 /
b110 &
b110 .
b1000 *
#90000
0#
#95000
1!
10
b0 "
b0 -
b0 5
1#
#96000
b0 1
b0 2
b0 $
b0 +
b0 '
b0 /
b0 &
b0 .
b1001 *
#100000
0#
#105000
1#
#106000
b1000 3
b11 1
b101 2
b0 %
b0 ,
b10 '
b10 /
b1 &
b1 .
b1011 *
#110000
0#
#115000
b0 4
0!
00
b1000 "
b1000 -
b1000 5
1#
#116000
b11 %
b11 ,
b1101 *
#120000
0#
#125000
b11 4
1#
#126000
b1110 *
#130000
0#
#135000
1#
#136000
b0 3
b1 1
b11111111 2
b110 '
b110 /
b101 &
b101 .
b1111 *
#140000
0#
#145000
1!
10
b0 "
b0 -
b0 5
1#
#146000
b10000 *
