designs/alu_pipelined/rtl/pipelined_alu.sv
module pipelined_alu (
    input  logic       clk,
    input  logic       rst,

    input  logic [2:0] rs1,
    input  logic [2:0] rs2,
    input  logic [2:0] rd,
    input  logic [2:0] opcode,

    output logic [7:0] result,
    output logic       zero
);

    // ============================================================
    // Register File
    // 8 registers × 8 bits
    // R0 is hardwired to zero
    // ============================================================

    logic [7:0] reg_file [0:7];

    logic [7:0] operand_a;
    logic [7:0] operand_b;

    // Combinational register-file reads
    assign operand_a = (rs1 == 3'b000) ? 8'h00 : reg_file[rs1];
    assign operand_b = (rs2 == 3'b000) ? 8'h00 : reg_file[rs2];


    // ============================================================
    // ALU Combinational Logic
    // ============================================================

    logic [7:0] alu_result;

    always_comb begin
        case (opcode)

            3'b000: alu_result = operand_a + operand_b; // ADD
            3'b001: alu_result = operand_a - operand_b; // SUB
            3'b010: alu_result = operand_a & operand_b; // AND
            3'b011: alu_result = operand_a | operand_b; // OR
            3'b100: alu_result = operand_a ^ operand_b; // XOR
            3'b101: alu_result = ~operand_a;            // NOT
            3'b110: alu_result = operand_a << 1;        // SHIFT LEFT
            3'b111: alu_result = operand_a >> 1;        // SHIFT RIGHT

            default: alu_result = 8'h00;

        endcase
    end


    // ============================================================
    // Pipeline Register
    // ============================================================

    logic [7:0] pipeline_result;
    logic [2:0] pipeline_rd;
    logic       pipeline_valid;

    logic pipeline_zero;

    assign pipeline_zero = (pipeline_result == 8'h00);


    // ============================================================
    // Sequential Logic
    //
    // Stage 2:
    //   Write previous pipeline result to register file
    //
    // Stage 1:
    //   Capture current ALU result into pipeline register
    // ============================================================

    integer i;

    always_ff @(posedge clk) begin

        if (rst) begin

            // Reset register file
            for (i = 0; i < 8; i = i + 1)
                reg_file[i] <= 8'h00;

            // Reset pipeline
            pipeline_result <= 8'h00;
            pipeline_rd     <= 3'b000;
            pipeline_valid  <= 1'b0;

        end
        else begin

            // ----------------------------------------------------
            // Stage 2: Writeback
            // ----------------------------------------------------

            if (pipeline_valid && (pipeline_rd != 3'b000))
                reg_file[pipeline_rd] <= pipeline_result;


            // ----------------------------------------------------
            // Stage 1: Capture ALU result
            // ----------------------------------------------------

            pipeline_result <= alu_result;
            pipeline_rd     <= rd;
            pipeline_valid  <= 1'b1;

        end

    end


    // ============================================================
    // Output
    //
    // Outputs represent the completed pipeline stage.
    // They are combinational views of the pipeline register.
    // ============================================================

    assign result = pipeline_result;
    assign zero   = pipeline_zero;

endmodule

designs/alu_pipelined/rtl/variations/verification/raw_hazard_tb.sv
`timescale 1ns/1ps

module pipelined_alu_tb;

    logic       clk;
    logic       rst;

    logic [2:0] rs1;
    logic [2:0] rs2;
    logic [2:0] rd;
    logic [2:0] opcode;

    logic [7:0] result;
    logic       zero;


    // ------------------------------------------------------------
    // DUT
    // ------------------------------------------------------------

    pipelined_alu dut (
        .clk    (clk),
        .rst    (rst),
        .rs1    (rs1),
        .rs2    (rs2),
        .rd     (rd),
        .opcode (opcode),
        .result (result),
        .zero   (zero)
    );


    // ------------------------------------------------------------
    // Clock
    // ------------------------------------------------------------

    initial begin
        clk = 1'b0;
        forever #5 clk = ~clk;
    end


    // ------------------------------------------------------------
    // Test counters
    // ------------------------------------------------------------

    integer tests_passed = 0;
    integer tests_failed = 0;


    // ------------------------------------------------------------
    // Reset
    // ------------------------------------------------------------

    task reset_dut;
        begin
            rst    = 1'b1;
            rs1    = 3'b000;
            rs2    = 3'b000;
            rd     = 3'b000;
            opcode = 3'b000;

            @(posedge clk);
            @(posedge clk);

            rst = 1'b0;

            #1;

            // Simulation-only initialization
            dut.reg_file[0] = 8'h00;
            dut.reg_file[1] = 8'h05;
            dut.reg_file[2] = 8'h03;
            dut.reg_file[3] = 8'h00;
            dut.reg_file[4] = 8'h00;
            dut.reg_file[5] = 8'h0F;
            dut.reg_file[6] = 8'hF0;
            dut.reg_file[7] = 8'hAA;
        end
    endtask


    // ------------------------------------------------------------
    // Apply an instruction
    // ------------------------------------------------------------

    task apply_instruction(
        input [2:0] in_rs1,
        input [2:0] in_rs2,
        input [2:0] in_rd,
        input [2:0] in_opcode
    );
        begin
            rs1    = in_rs1;
            rs2    = in_rs2;
            rd     = in_rd;
            opcode = in_opcode;
        end
    endtask


    // ------------------------------------------------------------
    // Check result
    // ------------------------------------------------------------

    task check_result(
        input [7:0] expected,
        input [127:0] test_name
    );
        begin

            if (result === expected) begin
                $display("[PASS] %s : result = %h",
                         test_name, result);
                tests_passed = tests_passed + 1;
            end
            else begin
                $display("[FAIL] %s : expected = %h, got = %h",
                         test_name, expected, result);
                tests_failed = tests_failed + 1;
            end

        end
    endtask


    // ------------------------------------------------------------
    // Main test
    // ------------------------------------------------------------

    initial begin

        $dumpfile("raw_hazard.vcd");
        $dumpvars(0, pipelined_alu_tb);

        reset_dut();


        // ========================================================
        // Test 1
        //
        // Establish:
        //
        // R3 = R1 + R2
        //
        // 5 + 3 = 8
        // ========================================================

        $display("");
        $display("==============================================");
        $display("TEST 1: Generate R3");
        $display("==============================================");

        apply_instruction(
            3'd1,
            3'd2,
            3'd3,
            3'b000       // ADD
        );

        @(posedge clk);
        #1;

        check_result(
            8'h08,
            "R1 + R2 -> R3"
        );


        // ========================================================
        // Test 2
        //
        // RAW HAZARD
        //
        // Immediately use R3:
        //
        // R4 = R3 + R1
        //
        // Expected:
        //
        // R4 = 8 + 5 = 13
        //
        // Golden RTL does NOT handle this hazard.
        // Hazard-fixed RTL stalls for one cycle.
        // ========================================================

        $display("");
        $display("==============================================");
        $display("TEST 2: RAW Hazard");
        $display("==============================================");

        apply_instruction(
            3'd3,
            3'd1,
            3'd4,
            3'b000       // ADD
        );

        @(posedge clk);
        #1;

        // Hazard-fixed design should still have R3's result
        // because the dependent instruction was stalled.

        check_result(
            8'h08,
            "RAW hazard causes one-cycle stall"
        );


        // --------------------------------------------------------
        // Next cycle: dependent instruction should now execute.
        // --------------------------------------------------------

        @(posedge clk);
        #1;

        check_result(
            8'h0D,
            "Dependent instruction uses updated R3"
        );


        // --------------------------------------------------------
        // Verify actual register writeback.
        // --------------------------------------------------------

        @(posedge clk);
        #1;

        if (dut.reg_file[4] === 8'h0D) begin
            $display("[PASS] R4 writeback = 0D");
            tests_passed = tests_passed + 1;
        end
        else begin
            $display("[FAIL] R4 writeback : expected 0D, got %h",
                     dut.reg_file[4]);
            tests_failed = tests_failed + 1;
        end


        // ========================================================
        // Test 3
        //
        // No hazard.
        //
        // R5 = R1 + R2
        //
        // Makes sure normal operation still works.
        // ========================================================

        $display("");
        $display("==============================================");
        $display("TEST 3: Non-dependent instruction");
        $display("==============================================");

        apply_instruction(
            3'd1,
            3'd2,
            3'd5,
            3'b000
        );

        @(posedge clk);
        #1;

        check_result(
            8'h08,
            "Independent ADD"
        );


        // ========================================================
        // Test 4
        //
        // Hazard through rs2 instead of rs1.
        //
        // R6 = R1 + R2
        // R7 = R1 + R6
        //
        // ========================================================

        $display("");
        $display("==============================================");
        $display("TEST 4: RAW hazard through rs2");
        $display("==============================================");

        apply_instruction(
            3'd1,
            3'd2,
            3'd6,
            3'b000
        );

        @(posedge clk);
        #1;

        check_result(
            8'h08,
            "Generate R6"
        );


        // Dependent instruction
        apply_instruction(
            3'd1,
            3'd6,
            3'd7,
            3'b000
        );

        @(posedge clk);
        #1;

        check_result(
            8'h08,
            "Hazard stall holds R6 result"
        );


        @(posedge clk);
        #1;

        check_result(
            8'h0D,
            "R1 + updated R6"
        );


        // --------------------------------------------------------
        // End
        // --------------------------------------------------------

        $display("");
        $display("==============================================");
        $display("RAW HAZARD TEST SUMMARY");
        $display("==============================================");
        $display("Tests Passed : %0d", tests_passed);
        $display("Tests Failed : %0d", tests_failed);

        if (tests_failed == 0)
            $display("******** ALL HAZARD TESTS PASSED ********");
        else
            $display("******** HAZARD TEST FAILED ********");

        $display("==============================================");

        $finish;

    end

endmodule

designs/alu_pipelined/raw_hazard.vcd
$date
	Tue Sep  8 15:28:15 2026
$end
$version
	Icarus Verilog
$end
$timescale
	1ps
$end
$scope module pipelined_alu_tb $end
$var wire 1 ! zero $end
$var wire 8 " result [7:0] $end
$var reg 1 # clk $end
$var reg 3 $ opcode [2:0] $end
$var reg 3 % rd [2:0] $end
$var reg 3 & rs1 [2:0] $end
$var reg 3 ' rs2 [2:0] $end
$var reg 1 ( rst $end
$var integer 32 ) tests_failed [31:0] $end
$var integer 32 * tests_passed [31:0] $end
$scope module dut $end
$var wire 1 # clk $end
$var wire 3 + opcode [2:0] $end
$var wire 3 , rd [2:0] $end
$var wire 8 - result [7:0] $end
$var wire 3 . rs1 [2:0] $end
$var wire 3 / rs2 [2:0] $end
$var wire 1 ( rst $end
$var wire 1 ! zero $end
$var wire 1 0 pipeline_zero $end
$var wire 8 1 operand_b [7:0] $end
$var wire 8 2 operand_a [7:0] $end
$var reg 8 3 alu_result [7:0] $end
$var reg 3 4 pipeline_rd [2:0] $end
$var reg 8 5 pipeline_result [7:0] $end
$var reg 1 6 pipeline_valid $end
$var integer 32 7 i [31:0] $end
$upscope $end
$scope task apply_instruction $end
$var reg 3 8 in_opcode [2:0] $end
$var reg 3 9 in_rd [2:0] $end
$var reg 3 : in_rs1 [2:0] $end
$var reg 3 ; in_rs2 [2:0] $end
$upscope $end
$scope task check_result $end
$var reg 8 < expected [7:0] $end
$var reg 128 = test_name [127:0] $end
$upscope $end
$scope task reset_dut $end
$upscope $end
$upscope $end
$enddefinitions $end
$comment Show the parameter values. $end
$dumpall
$end
#0
$dumpvars
bx =
bx <
bx ;
bx :
bx 9
bx 8
bx 7
x6
bx 5
bx 4
b0 3
b0 2
b0 1
x0
b0 /
b0 .
bx -
b0 ,
b0 +
b0 *
b0 )
1(
b0 '
b0 &
b0 %
b0 $
0#
bx "
x!
$end
#5000
06
b0 4
1!
10
b0 "
b0 -
b0 5
b1000 7
1#
#10000
0#
#15000
0(
b1000 7
1#
#16000
b1000 3
b11 1
b101 2
b11 %
b11 ,
b10 '
b10 /
b1 &
b1 .
b0 8
b11 9
b10 ;
b1 :
#20000
0#
#25000
16
b11 4
0!
00
b1000 "
b1000 -
b1000 5
1#
#26000
b101 3
b101 1
b0 2
b100 %
b100 ,
b1 '
b1 /
b11 &
b11 .
b100 9
b1 ;
b11 :
b1 *
b1010010001100010010000000101011001000000101001000110010001000000010110100111110001000000101001000110011 =
b1000 <
#30000
0#
#35000
b1101 3
b1000 2
b100 4
b101 "
b101 -
b101 5
1#
#36000
b1 )
b100000011011110110111001100101001011010110001101111001011000110110110001100101001000000111001101110100011000010110110001101100 =
#40000
0#
#45000
b1101 "
b1101 -
b1101 5
1#
#46000
b10 *
b100000011101010111001101100101011100110010000001110101011100000110010001100001011101000110010101100100001000000101001000110011 =
b1101 <
#50000
0#
#55000
1#
#56000
b1000 3
b11 1
b101 2
b101 %
b101 ,
b10 '
b10 /
b1 &
b1 .
b101 9
b10 ;
b1 :
b11 *
#60000
0#
#65000
b101 4
b1000 "
b1000 -
b1000 5
1#
#66000
b110 %
b110 ,
b110 9
b100 *
b10010010110111001100100011001010111000001100101011011100110010001100101011011100111010000100000010000010100010001000100 =
b1000 <
#70000
0#
#75000
b110 4
1#
#76000
b11110101 3
b11110000 1
b111 %
b111 ,
b110 '
b110 /
b111 9
b110 ;
b101 *
b100011101100101011011100110010101110010011000010111010001100101001000000101001000110110 =
#80000
0#
#85000
b1101 3
b1000 1
b111 4
b11110101 "
b11110101 -
b11110101 5
1#
#86000
b10 )
b100000011010000110111101101100011001000111001100100000010100100011011000100000011100100110010101110011011101010110110001110100 =
#90000
0#
#95000
b1101 "
b1101 -
b1101 5
1#
#96000
b110 *
b10100100011000100100000001010110010000001110101011100000110010001100001011101000110010101100100001000000101001000110110 =
b1101 <
